{"_wandb":{"runtime":127},"train_loss":0.08869178977476569,"val_loss":0.11437657173664244,"Sample Images":{"width":1000,"height":1000,"_type":"image-file","sha256":"98c7240c4357bd360905556f6bc7cf61fa3e526b88309fd177f241bea48fa844","size":34705,"path":"media/images/Sample Images_0_98c7240c4357bd360905.png","format":"png"},"_runtime":127.835554092,"train_accuracy":0.8665166666666667,"Confusion Matrix":{"sha256":"c6b83ad56ed78eb170badd8548734f865c876757086032e435e41e14320f2242","size":49404,"path":"media/images/Confusion Matrix_11_c6b83ad56ed78eb170ba.png","format":"png","width":1000,"height":800,"_type":"image-file"},"_timestamp":1.7422221881368463e+09,"val_accuracy":0.8505,"_step":11,"epoch":10}